{
  "Projects": [
    {
      "GlobalData": {
        "ProjectId": "b631b5a1-2ee6-4b4c-904a-8a91b5e63c9a",
        "ProjectName": "secondRepo",
        "DBTypeName": "SQL Server",
        "Environments": [
          {
            "EnvironmentId": "6c1f1399-578d-478e-8df8-4ae4a83070d9",
            "EnvironmentName": "Dev_Env_1",
            "EnvironmentType": "DEV",
            "Databases": [
              {
                "DatabaseId": "b3719d80-6a37-4da2-b24d-6685c9936966",
                "DatabaseAliasName": "alias1",
                "DatabaseConnectionDetails": null,
                "RepositoryDetails": {
                  "$type": "DOP.SourceControl.ExternalSourceControl.Git.Models.GitRepositoryDetails, DOP.SourceControl.ExternalSourceControl.Git",
                  "RemoteRepositoryURL": "https://github.com/KyryloZ-DBM/secondRepo.git",
                  "BranchName": "main"
                }
              }
            ]
          }
        ],
        "SourceControlPathType": 0,
        "Configuration": {
          "BuildMigrationScriptAutomatically": true,
          "BuildMethod": 1,
          "NumberOfRevisionsInViewHistory": 10,
          "NumberOfTagsInBuildOptions": 10,
          "BuildDeploymentScriptOnPush": false,
          "PreventCommitObjectWithConflict": false
        },
        "ProjectArchitecture": 0,
        "LocalDirectory": "C:\\Users\\admin\\Documents\\secondRepo"
      },
      "UserData": [
        {
          "UserName": "KyryloZ-DBM",
          "DatabasesData": [
            {
              "DatabaseId": "b3719d80-6a37-4da2-b24d-6685c9936966",
              "DatabaseAliasName": "alias1",
              "DatabaseConnectionDetails": {
                "DBTypeName": "SQL Server",
                "Host": "localhost",
                "AuthenticationType": 1,
                "Username": "sa",
                "Password": "do1NBD0OcmAl1jAcpH7iWg==",
                "DatabaseName": "alias1"
              },
              "RepositoryCredentials": {
                "UserName": "KyryloZ-DBM",
                "Password": "8Bx04GkOSgJWZdFvYEe4T2UdLGizwUyNBuFOVXQLlekRxJPpNowp59kfoOHK++d4"
              }
            }
          ]
        }
      ]
    }
  ],
  "GlobalConfigurations": null
}